blooper/__init__.py
blooper/hello.py
blooper-1.0.0.dist-info/METADATA
blooper-1.0.0.dist-info/WHEEL
blooper-1.0.0.dist-info/top_level.txt
blooper-1.0.0.dist-info/RECORD
